{
"meta":{"test_sets":[],"test_metrics":[],"learn_metrics":[{"best_value":"Min","name":"RMSE"}],"launch_mode":"Train","parameters":"","iteration_count":100,"learn_sets":["learn"],"name":"experiment"},
"iterations":[
{"learn":[13.97360516],"iteration":0,"passed_time":0.001052450941,"remaining_time":0.1041926431},
{"learn":[13.14243715],"iteration":1,"passed_time":0.001459056987,"remaining_time":0.07149379236},
{"learn":[12.30686157],"iteration":2,"passed_time":0.001857955059,"remaining_time":0.06007388024},
{"learn":[11.58326243],"iteration":3,"passed_time":0.002326974863,"remaining_time":0.0558473967},
{"learn":[10.93889872],"iteration":4,"passed_time":0.002725372958,"remaining_time":0.05178208621},
{"learn":[10.39697124],"iteration":5,"passed_time":0.003159144405,"remaining_time":0.04949326234},
{"learn":[9.905832907],"iteration":6,"passed_time":0.003549042897,"remaining_time":0.04715156991},
{"learn":[9.478095839],"iteration":7,"passed_time":0.004004771653,"remaining_time":0.04605487401},
{"learn":[9.089630934],"iteration":8,"passed_time":0.004400753195,"remaining_time":0.04449650452},
{"learn":[8.682481132],"iteration":9,"passed_time":0.004792818252,"remaining_time":0.04313536427},
{"learn":[8.311486609],"iteration":10,"passed_time":0.005175050434,"remaining_time":0.04187086261},
{"learn":[7.994635464],"iteration":11,"passed_time":0.005621946269,"remaining_time":0.04122760598},
{"learn":[7.72986343],"iteration":12,"passed_time":0.006071258658,"remaining_time":0.04063073102},
{"learn":[7.451662134],"iteration":13,"passed_time":0.006470865031,"remaining_time":0.03974959947},
{"learn":[7.223669553],"iteration":14,"passed_time":0.006883595792,"remaining_time":0.03900704282},
{"learn":[7.037790984],"iteration":15,"passed_time":0.0072459539,"remaining_time":0.03804125798},
{"learn":[6.864177722],"iteration":16,"passed_time":0.007591354466,"remaining_time":0.03706367181},
{"learn":[6.704872208],"iteration":17,"passed_time":0.007974544938,"remaining_time":0.03632848249},
{"learn":[6.564984916],"iteration":18,"passed_time":0.008322445387,"remaining_time":0.03547989876},
{"learn":[6.443738293],"iteration":19,"passed_time":0.008670679154,"remaining_time":0.03468271662},
{"learn":[6.339077751],"iteration":20,"passed_time":0.009054494596,"remaining_time":0.03406214634},
{"learn":[6.232902237],"iteration":21,"passed_time":0.009394853731,"remaining_time":0.03330902686},
{"learn":[6.129649777],"iteration":22,"passed_time":0.009821375515,"remaining_time":0.03288025716},
{"learn":[6.034904993],"iteration":23,"passed_time":0.01030001987,"remaining_time":0.03261672959},
{"learn":[5.959636498],"iteration":24,"passed_time":0.01068325201,"remaining_time":0.03204975602},
{"learn":[5.903184681],"iteration":25,"passed_time":0.01106235933,"remaining_time":0.03148517657},
{"learn":[5.835713241],"iteration":26,"passed_time":0.01141434293,"remaining_time":0.03086100125},
{"learn":[5.783362958],"iteration":27,"passed_time":0.01176874307,"remaining_time":0.03026248219},
{"learn":[5.735615182],"iteration":28,"passed_time":0.01210160256,"remaining_time":0.02962806143},
{"learn":[5.690679745],"iteration":29,"passed_time":0.01246966873,"remaining_time":0.02909589371},
{"learn":[5.644820469],"iteration":30,"passed_time":0.01285377583,"remaining_time":0.02861001717},
{"learn":[5.602773068],"iteration":31,"passed_time":0.01327929766,"remaining_time":0.02821850753},
{"learn":[5.559104016],"iteration":32,"passed_time":0.01367702912,"remaining_time":0.02776851367},
{"learn":[5.527529923],"iteration":33,"passed_time":0.01408496844,"remaining_time":0.02734140932},
{"learn":[5.490596365],"iteration":34,"passed_time":0.01451136523,"remaining_time":0.02694967828},
{"learn":[5.461101985],"iteration":35,"passed_time":0.01487634821,"remaining_time":0.02644684127},
{"learn":[5.43659586],"iteration":36,"passed_time":0.0152755796,"remaining_time":0.02600977068},
{"learn":[5.418770412],"iteration":37,"passed_time":0.01567485266,"remaining_time":0.0255747596},
{"learn":[5.398865731],"iteration":38,"passed_time":0.01620286971,"remaining_time":0.02534295006},
{"learn":[5.37458737],"iteration":39,"passed_time":0.0166265583,"remaining_time":0.02493983744},
{"learn":[5.359343833],"iteration":40,"passed_time":0.01703145609,"remaining_time":0.02450868071},
{"learn":[5.340762809],"iteration":41,"passed_time":0.01741410492,"remaining_time":0.02404804965},
{"learn":[5.326774645],"iteration":42,"passed_time":0.01782200257,"remaining_time":0.02362451504},
{"learn":[5.304905752],"iteration":43,"passed_time":0.01822165061,"remaining_time":0.02319119168},
{"learn":[5.290594658],"iteration":44,"passed_time":0.01861500727,"remaining_time":0.02275167555},
{"learn":[5.272783913],"iteration":45,"passed_time":0.01898682327,"remaining_time":0.02228887949},
{"learn":[5.245040627],"iteration":46,"passed_time":0.01953854755,"remaining_time":0.02203283022},
{"learn":[5.231972111],"iteration":47,"passed_time":0.019922363,"remaining_time":0.02158255991},
{"learn":[5.220122657],"iteration":48,"passed_time":0.02032851073,"remaining_time":0.02115824586},
{"learn":[5.204435513],"iteration":49,"passed_time":0.02081648798,"remaining_time":0.02081648798},
{"learn":[5.187726577],"iteration":50,"passed_time":0.02124530133,"remaining_time":0.02041215226},
{"learn":[5.175958482],"iteration":51,"passed_time":0.02163349157,"remaining_time":0.01996937683},
{"learn":[5.16722965],"iteration":52,"passed_time":0.02201422382,"remaining_time":0.01952204754},
{"learn":[5.157366907],"iteration":53,"passed_time":0.02245920308,"remaining_time":0.01913191373},
{"learn":[5.152177099],"iteration":54,"passed_time":0.02262886183,"remaining_time":0.01851452332},
{"learn":[5.134325072],"iteration":55,"passed_time":0.02305896679,"remaining_time":0.01811775962},
{"learn":[5.124752677],"iteration":56,"passed_time":0.0234605314,"remaining_time":0.01769829562},
{"learn":[5.113079087],"iteration":57,"passed_time":0.02384288858,"remaining_time":0.01726554},
{"learn":[5.102684382],"iteration":58,"passed_time":0.02423253708,"remaining_time":0.01683955967},
{"learn":[5.091605221],"iteration":59,"passed_time":0.02472968057,"remaining_time":0.01648645372},
{"learn":[5.07953187],"iteration":60,"passed_time":0.02517236827,"remaining_time":0.01609380922},
{"learn":[5.059643725],"iteration":61,"passed_time":0.02554522589,"remaining_time":0.01565675135},
{"learn":[5.049051504],"iteration":62,"passed_time":0.02598249717,"remaining_time":0.01525956183},
{"learn":[5.034240841],"iteration":63,"passed_time":0.02636497934,"remaining_time":0.01483030088},
{"learn":[5.023733483],"iteration":64,"passed_time":0.02673871192,"remaining_time":0.01439776796},
{"learn":[5.005883971],"iteration":65,"passed_time":0.0272512297,"remaining_time":0.01403851227},
{"learn":[4.999509503],"iteration":66,"passed_time":0.02776687233,"remaining_time":0.0136762207},
{"learn":[4.986320242],"iteration":67,"passed_time":0.02815043778,"remaining_time":0.01324726484},
{"learn":[4.97160101],"iteration":68,"passed_time":0.02855571056,"remaining_time":0.01282937721},
{"learn":[4.963797294],"iteration":69,"passed_time":0.02908035277,"remaining_time":0.01246300833},
{"learn":[4.95998097],"iteration":70,"passed_time":0.02946279327,"remaining_time":0.01203409866},
{"learn":[4.950555769],"iteration":71,"passed_time":0.0298533584,"remaining_time":0.01160963938},
{"learn":[4.939671333],"iteration":72,"passed_time":0.03023975706,"remaining_time":0.01118456768},
{"learn":[4.926439306],"iteration":73,"passed_time":0.03061748945,"remaining_time":0.01075749629},
{"learn":[4.908394892],"iteration":74,"passed_time":0.03103530331,"remaining_time":0.0103451011},
{"learn":[4.901772659],"iteration":75,"passed_time":0.03147761602,"remaining_time":0.009940299796},
{"learn":[4.890941435],"iteration":76,"passed_time":0.03188759691,"remaining_time":0.00952486661},
{"learn":[4.883029382],"iteration":77,"passed_time":0.03228711995,"remaining_time":0.009106623577},
{"learn":[4.875668403],"iteration":78,"passed_time":0.03271726657,"remaining_time":0.008696994911},
{"learn":[4.862134925],"iteration":79,"passed_time":0.03314607991,"remaining_time":0.008286519978},
{"learn":[4.857774242],"iteration":80,"passed_time":0.03353593674,"remaining_time":0.007866454297},
{"learn":[4.851502589],"iteration":81,"passed_time":0.03399333209,"remaining_time":0.007461950946},
{"learn":[4.841712],"iteration":82,"passed_time":0.03438585546,"remaining_time":0.007042886057},
{"learn":[4.833397754],"iteration":83,"passed_time":0.0348261266,"remaining_time":0.006633547924},
{"learn":[4.82417587],"iteration":84,"passed_time":0.035296563,"remaining_time":0.006228805236},
{"learn":[4.809835079],"iteration":85,"passed_time":0.03576587446,"remaining_time":0.005822351656},
{"learn":[4.801642535],"iteration":86,"passed_time":0.03614923159,"remaining_time":0.005401609318},
{"learn":[4.793904391],"iteration":87,"passed_time":0.03658704451,"remaining_time":0.004989142434},
{"learn":[4.787002624],"iteration":88,"passed_time":0.036962777,"remaining_time":0.004568433112},
{"learn":[4.781389274],"iteration":89,"passed_time":0.03734225931,"remaining_time":0.004149139923},
{"learn":[4.763563448],"iteration":90,"passed_time":0.03777998891,"remaining_time":0.003736482419},
{"learn":[4.759690384],"iteration":91,"passed_time":0.03815813795,"remaining_time":0.003318098952},
{"learn":[4.751802532],"iteration":92,"passed_time":0.03855274455,"remaining_time":0.002901819482},
{"learn":[4.733707661],"iteration":93,"passed_time":0.03894601789,"remaining_time":0.002485916035},
{"learn":[4.72153991],"iteration":94,"passed_time":0.03935645709,"remaining_time":0.002071392478},
{"learn":[4.719695468],"iteration":95,"passed_time":0.03972314833,"remaining_time":0.00165513118},
{"learn":[4.705008761],"iteration":96,"passed_time":0.04012304635,"remaining_time":0.001240918959},
{"learn":[4.697331985],"iteration":97,"passed_time":0.04060069075,"remaining_time":0.0008285855256},
{"learn":[4.689067984],"iteration":98,"passed_time":0.04099683895,"remaining_time":0.0004141094844},
{"learn":[4.681104009],"iteration":99,"passed_time":0.04140436162,"remaining_time":0}
]}